app/__init__.py
app/main.py
app/core/__init__.py
app/core/auth.py
app/core/imports.py
app/core/manifest.py
app/core/prompts_provider.py
app/core/registry.py
app/core/settings.py
app/core/templates.py
app/services/__init__.py
app/services/constants.py
app/services/data_product/__init__.py
app/services/data_product/models/__init__.py
app/services/data_product/models/attach_business_domain_to_data_product.py
app/services/data_product/models/attach_contract_to_data_product.py
app/services/data_product/models/create_url_data_product.py
app/services/data_product/models/publish_data_product.py
app/services/data_product/tools/__init__.py
app/services/data_product/tools/attach_business_domain_to_data_product.py
app/services/data_product/tools/attach_contract_to_data_product.py
app/services/data_product/tools/create_url_data_product.py
app/services/data_product/tools/publish_data_product.py
app/services/data_product/utils/__init__.py
app/services/data_product/utils/common_utils.py
app/services/data_product/utils/data_product_creation_utils.py
app/services/data_protection_rules/__init__.py
app/services/data_protection_rules/models/__init__.py
app/services/data_protection_rules/models/create_rule.py
app/services/data_protection_rules/tools/__init__.py
app/services/data_protection_rules/tools/create_rule.py
app/services/lineage/__init__.py
app/services/lineage/models/__init__.py
app/services/lineage/models/get_lineage_graph.py
app/services/lineage/models/get_lineage_graph_by_cams_id.py
app/services/lineage/models/lineage_asset.py
app/services/lineage/models/search_lineage_assets.py
app/services/lineage/tools/__init__.py
app/services/lineage/tools/get_lineage_graph.py
app/services/lineage/tools/get_lineage_graph_by_cams_id.py
app/services/lineage/tools/search_lineage_assets.py
app/services/lineage/tools/utils.py
app/services/search/__init__.py
app/services/search/models/__init__.py
app/services/search/models/search_asset.py
app/services/search/tools/__init__.py
ibm_data_intelligence_mcp_server-0.0.2.dist-info/licenses/LICENSE
ibm_data_intelligence_mcp_server-0.0.2.dist-info/METADATA
ibm_data_intelligence_mcp_server-0.0.2.dist-info/WHEEL
ibm_data_intelligence_mcp_server-0.0.2.dist-info/entry_points.txt
ibm_data_intelligence_mcp_server-0.0.2.dist-info/top_level.txt
ibm_data_intelligence_mcp_server-0.0.2.dist-info/RECORD
